webdav4/__init__.py
webdav4/_version.py
webdav4/callback.py
webdav4/cli.py
webdav4/client.py
webdav4/date_utils.py
webdav4/fs_utils.py
webdav4/fsspec.py
webdav4/func_utils.py
webdav4/http.py
webdav4/multistatus.py
webdav4/retry.py
webdav4/stream.py
webdav4/types.py
webdav4/urls.py
webdav4/version.py
webdav4-0.9.8.dist-info/METADATA
webdav4-0.9.8.dist-info/WHEEL
webdav4-0.9.8.dist-info/entry_points.txt
webdav4-0.9.8.dist-info/licenses/LICENSE
webdav4-0.9.8.dist-info/RECORD
