Metadata-Version: 2.1
Name: webdav4
Version: 0.9.8
Summary: WebDAV client library with an fsspec-based filesystem and a CLI
Project-URL: Bug Tracker, https://github.com/skshetry/webdav4/issues
Project-URL: Documentation, https://skshetry.github.io/webdav4
Project-URL: Source Code, https://github.com/skshetry/webdav4
Author-email: Saugat Pachhai <suagatchhetri@outlook.com>
License-File: LICENSE
Keywords: fsspec,webdav,webdav-cli,webdav-client
Classifier: Development Status :: 4 - Beta
Classifier: Programming Language :: Python :: 3
Classifier: Programming Language :: Python :: 3.7
Classifier: Programming Language :: Python :: 3.8
Classifier: Programming Language :: Python :: 3.9
Classifier: Programming Language :: Python :: 3.10
Classifier: Programming Language :: Python :: 3.11
Requires-Python: >=3.7
Requires-Dist: httpx<1.0.0,>=0.20
Requires-Dist: python-dateutil>=2.8.1
Provides-Extra: all
Requires-Dist: webdav4[fsspec,http2]; extra == 'all'
Provides-Extra: dev
Requires-Dist: webdav4[docs,fsspec,http2,qa,tests]; extra == 'dev'
Provides-Extra: docs
Requires-Dist: furo==2022.9.29; extra == 'docs'
Requires-Dist: myst-parser==0.18.1; extra == 'docs'
Requires-Dist: sphinx-copybutton==0.5; extra == 'docs'
Requires-Dist: sphinx==5.3; extra == 'docs'
Provides-Extra: fsspec
Requires-Dist: fsspec>=2021.7; extra == 'fsspec'
Provides-Extra: http2
Requires-Dist: httpx[http2]<1.0.0,>=0.20; extra == 'http2'
Provides-Extra: qa
Requires-Dist: mypy==0.982; extra == 'qa'
Requires-Dist: pre-commit; extra == 'qa'
Requires-Dist: pylint-pytest==1.1.2; extra == 'qa'
Requires-Dist: pylint==2.15.5; extra == 'qa'
Requires-Dist: types-pkg-resources; extra == 'qa'
Requires-Dist: types-python-dateutil; extra == 'qa'
Provides-Extra: tests
Requires-Dist: cheroot; extra == 'tests'
Requires-Dist: colorama; extra == 'tests'
Requires-Dist: pytest; extra == 'tests'
Requires-Dist: pytest-cov; extra == 'tests'
Requires-Dist: pytest-xdist; extra == 'tests'
Requires-Dist: typing-extensions; extra == 'tests'
Requires-Dist: wsgidav; extra == 'tests'
